pytest_print/__init__.py
pytest_print/py.typed
pytest_print-1.2.0.dist-info/METADATA
pytest_print-1.2.0.dist-info/WHEEL
pytest_print-1.2.0.dist-info/entry_points.txt
pytest_print-1.2.0.dist-info/licenses/LICENSE
pytest_print-1.2.0.dist-info/RECORD
